test/__init__.py
webullsdktradeeventscore/__init__.py
webullsdktradeeventscore/default_retry_policy.py
webullsdktradeeventscore/events_client.py
webullsdktradeeventscore/events_pb2.py
webullsdktradeeventscore/events_pb2_grpc.py
webullsdktradeeventscore/signature_composer.py
webull_python_sdk_trade_events_core-0.1.18.dist-info/METADATA
webull_python_sdk_trade_events_core-0.1.18.dist-info/WHEEL
webull_python_sdk_trade_events_core-0.1.18.dist-info/top_level.txt
webull_python_sdk_trade_events_core-0.1.18.dist-info/RECORD
